{
  "id": "module-2/chapter-2-gazebo-physics-simulation",
  "title": "Chapter 2: Physics Simulation in Gazebo",
  "description": "Estimated time Intermediate | Week: 6, Days 2-5",
  "source": "@site/docs/module-2/chapter-2-gazebo-physics-simulation.md",
  "sourceDirName": "module-2",
  "slug": "/module-2/chapter-2-gazebo-physics-simulation",
  "permalink": "/ai_native-textbook/docs/module-2/chapter-2-gazebo-physics-simulation",
  "draft": false,
  "unlisted": false,
  "tags": [
    {
      "inline": true,
      "label": "gazebo",
      "permalink": "/ai_native-textbook/docs/tags/gazebo"
    },
    {
      "inline": true,
      "label": "physics",
      "permalink": "/ai_native-textbook/docs/tags/physics"
    },
    {
      "inline": true,
      "label": "simulation",
      "permalink": "/ai_native-textbook/docs/tags/simulation"
    },
    {
      "inline": true,
      "label": "hands-on",
      "permalink": "/ai_native-textbook/docs/tags/hands-on"
    },
    {
      "inline": true,
      "label": "week-6",
      "permalink": "/ai_native-textbook/docs/tags/week-6"
    }
  ],
  "version": "current",
  "sidebarPosition": 2,
  "frontMatter": {
    "sidebar_position": 2,
    "sidebar_label": "Ch.2: Gazebo Physics",
    "title": "Chapter 2: Physics Simulation in Gazebo",
    "tags": [
      "gazebo",
      "physics",
      "simulation",
      "hands-on",
      "week-6"
    ],
    "difficulty": "Intermediate",
    "module": 2,
    "week": 6,
    "prerequisites": [
      "Chapter 1",
      "Ubuntu 22.04",
      "ROS 2 Humble"
    ],
    "estimated_time": "4-5 hours",
    "topics": [
      "gazebo",
      "sdf-urdf",
      "physics-engines",
      "ros2-integration",
      "sensors"
    ]
  },
  "sidebar": "tutorialSidebar",
  "previous": {
    "title": "Ch.1: Digital Twin Introduction",
    "permalink": "/ai_native-textbook/docs/module-2/chapter-1-digital-twin-introduction"
  },
  "next": {
    "title": "Ch.3: Sensor Simulation",
    "permalink": "/ai_native-textbook/docs/module-2/chapter-3-sensor-simulation"
  }
}